knn_fishmlserv/__init__.py
knn_fishmlserv/main.py
knn_fishmlserv-0.1.5.dist-info/METADATA
knn_fishmlserv-0.1.5.dist-info/WHEEL
knn_fishmlserv-0.1.5.dist-info/entry_points.txt
knn_fishmlserv-0.1.5.dist-info/top_level.txt
knn_fishmlserv-0.1.5.dist-info/RECORD
