Metadata-Version: 2.1
Name: knn_fishmlserv
Version: 0.1.5
Summary: Default template for PDM package
Author-email: kim <lsiwh32749@gmail.com>
License: MIT
Requires-Python: ==3.10.*
Requires-Dist: pandas>=2.0.3
Requires-Dist: pyarrow>=17.0.0
Requires-Dist: fastparquet>=2024.2.0
Requires-Dist: note>=0.5.2
Requires-Dist: scikit-learn>=1.5.1
Requires-Dist: matplotlib>=3.7.5
Requires-Dist: plotext>=5.2.8
Requires-Dist: jupyter>=1.1.1
Requires-Dist: notebook>=7.2.2
